[
  {
    "id": "be3f84f8-c454-47b1-9bdd-e3573bcb3eb5",
    "name": "Family TV Planner",
    "description": "Shows a shared household calendar on Android TV, syncing events from Google, Outlook, and iOS. Voice commands add or modify events, while reminders appear as on‑screen alerts, keeping families coordinated without checking phones.",
    "tags": [
      "calendar",
      "family",
      "tv",
      "productivity"
    ],
    "emoji": "📅",
    "device": "Android TV",
    "author": {
      "name": "Akhil",
      "color": "#7E57C2",
      "initials": "AK"
    },
    "position": {
      "x": -575.9503599450485,
      "y": -252.4196572054141
    },
    "createdAt": 1772392191013,
    "isForged": false,
    "forgedFrom": []
  },
  {
    "id": "820e598b-07f6-43d9-8348-911ff827448f",
    "name": "Local Gem Explorer",
    "description": "Explore unseen local spots from your couch: the app uses your phone’s location to surface nearby hidden restaurants, parks, art, and events, delivering short video tours and map navigation, letting you plan spontaneous outings directly from Android TV.",
    "tags": [
      "local",
      "discovery",
      "travel",
      "tv"
    ],
    "emoji": "📍",
    "device": "Android TV",
    "author": {
      "name": "Akhil",
      "color": "#7E57C2",
      "initials": "AK"
    },
    "position": {
      "x": -144.531265852105,
      "y": -297.47582814253076
    },
    "createdAt": 1772392535929,
    "isForged": false,
    "forgedFrom": []
  },
  {
    "id": "f3bbdb41-efdd-4763-b4aa-aae18f495ae8",
    "name": "HomeHub Explorer",
    "description": "HomeHub Explorer turns your Android TV into a shared family hub that syncs calendars, shows reminders, and lets you discover nearby hidden restaurants, parks, and events—all via voice. Plan outings, add events, and watch short video tours right on the big screen, keeping everyone coordinated and inspired.",
    "tags": [
      "family",
      "calendar",
      "local-discovery",
      "android-tv"
    ],
    "emoji": "📺",
    "device": "Android TV",
    "author": {
      "name": "Akhil",
      "color": "#7E57C2",
      "initials": "AK"
    },
    "position": {
      "x": 287.399092390262,
      "y": -256.60494711708617
    },
    "createdAt": 1772392604484,
    "isForged": true,
    "forgedFrom": [
      "be3f84f8-c454-47b1-9bdd-e3573bcb3eb5",
      "820e598b-07f6-43d9-8348-911ff827448f"
    ]
  }
]